segmenthee/__init__.py
segmenthee/cart_api.py
segmenthee/config.py
segmenthee/parser_api.py
segmenthee/shop.py
segmentheepy_vagy_az-1.1.5.dist-info/METADATA
segmentheepy_vagy_az-1.1.5.dist-info/WHEEL
segmentheepy_vagy_az-1.1.5.dist-info/top_level.txt
segmentheepy_vagy_az-1.1.5.dist-info/RECORD
