Metadata-Version: 2.1
Name: segmentheepy-vagy-az
Version: 1.1.5
Summary: Segmenthee library
Author: Michaletzky Tamás
License: MIT
Requires-Python: >=3.8
Requires-Dist: user-agents (==2.2.0)
Requires-Dist: xgboost (==1.4.0)
Requires-Dist: scikit-learn (==0.23.2)
